<?xml version="1.0" encoding="utf-8"?>
<actor version="1">
  <castshadow/>
  <group>
    <variant frequency="100" name="Keep">
      <animations>
        <animation event="0.5" load="0.0" name="attack_ranged" speed="100"/>
      </animations>
      <mesh>structural/uni_civil_center.dae</mesh>
      <props>
        <prop actor="props/structures/decals/dirt_6x6.xml" attachpoint="root"/>
        <prop actor="props/structures/decals/celt_barracks.xml" attachpoint="root"/>
        <prop actor="props/units/weapons/arrowbuilding_projectile.xml" attachpoint="loaded-projectile"/>
        <prop actor="props/units/weapons/arrowbuilding_projectile.xml" attachpoint="projectile"/>
        <prop actor="props/flora/bush_tempe_underbrush.xml" attachpoint="bush_1" maxheight="20" minheight="-20"/>
        <prop actor="flora/trees/apple_bloom.xml" attachpoint="bush_2" maxheight="20" minheight="-20"/>
        <prop actor="props/flora/bush_tempe_underbrush.xml" attachpoint="bush_2" maxheight="20" minheight="-20"/>
        <prop actor="props/flora/bush_tempe_underbrush.xml" attachpoint="bush_3" maxheight="20" minheight="-20"/>
        <prop actor="props/flora/bush_tempe_underbrush.xml" attachpoint="bush_4" maxheight="20" minheight="-20"/>
        <prop actor="props/flora/bush_tempe_underbrush.xml" attachpoint="bush_5" maxheight="20" minheight="-20"/>
        <prop actor="props/flora/bush_tempe_underbrush.xml" attachpoint="bush_6" maxheight="20" minheight="-20"/>
      </props>
      <textures>
        <texture file="structural/uni_struct.png" name="baseTex"/>
        <texture file="structural/uni_struct.png" name="normTex"/>
        <texture file="structural/ao/uni_civic_center_AO.png" name="aoTex"/>
      </textures>
    </variant>
  </group>
  <group>
    <variant frequency="100" name="Idle"/>
    <variant name="garrisoned">
      <props>
        <prop actor="props/structures/earth_ponies/fortress_pennant.xml" attachpoint="garrisoned"/>
      </props>
    </variant>
    <variant name="death">
      <props>
        <prop attachpoint="garrisoned"/>
        <prop actor="particle/destruction_smoke_large.xml" attachpoint="root"/>
        <prop actor="particle/destruction_dust_large.xml" attachpoint="root"/>
        <prop actor="particle/destruction_dust_large_gray.xml" attachpoint="root"/>
        <prop actor="props/structures/decals/gravel_5x5.xml" attachpoint="root"/>
      </props>
    </variant>
  </group>
  <material>player_trans_ao.xml</material>
</actor>
