<?xml version="1.0" encoding="utf-8"?>
<actor version="1">
  <castshadow/>
  <group>
    <variant frequency="100" name="Base">
      <mesh>props/weap_ballista_projectile.dae</mesh>
      <textures>
        <texture file="structural/pega_struct.png" name="baseTex"/>
        <texture name="specTex" file="null_white.dds"/>
        <texture file="default_norm.png" name="normTex"/>
      </textures>
    </variant>
  </group>
  <group>
    <variant frequency="1" name="1"/>
    <variant frequency="0" name="2">
      <props>
        <prop actor="particle/flame_jav.xml" attachpoint="root"/>
      </props>
    </variant>
  </group>
  <material>basic_trans_norm_spec.xml</material>
</actor>
